<?xml version = '1.0' encoding = 'UTF-8'?>
<SegmentOraclev10g class="oracle.dbtools.crest.model.design.storage.oracle.v10g.SegmentOraclev10g" name="Storage1" directorySegmentName="seg_0" id="1DAA069E-E2C7-64D7-184D-10AA80F379E6">
<createdBy>saeidhosseinipoor</createdBy>
<createdTime>2016-09-30 18:18:36 UTC</createdTime>
<ownerDesignName>Oracle File</ownerDesignName>
<initrans>2</initrans>
<maxTrans>255</maxTrans>
<scInitialExtent>65536</scInitialExtent>
<scMaxExtents>2147483645</scMaxExtents>
<scNextExtent>1048576</scNextExtent>
</SegmentOraclev10g>