<?xml version = '1.0' encoding = 'UTF-8'?>
<SegmentOraclev10g class="oracle.dbtools.crest.model.design.storage.oracle.v10g.SegmentOraclev10g" name="Storage1" directorySegmentName="seg_0" id="671BBA44-978D-C3FC-C7D6-FEB5B2BE026E">
<createdBy>saeidhosseinipoor</createdBy>
<createdTime>2016-11-21 15:16:42 UTC</createdTime>
<ownerDesignName>IP</ownerDesignName>
<maxTrans>255</maxTrans>
<scInitialExtent>65536</scInitialExtent>
<scMaxExtents>2147483645</scMaxExtents>
<scNextExtent>1048576</scNextExtent>
</SegmentOraclev10g>